dash_google_oauth/__init__.py
dash_google_oauth/auth.py
dash_google_oauth/google_auth.py
dash_google_oauth-1.2.dist-info/LICENSE
dash_google_oauth-1.2.dist-info/METADATA
dash_google_oauth-1.2.dist-info/WHEEL
dash_google_oauth-1.2.dist-info/top_level.txt
dash_google_oauth-1.2.dist-info/RECORD
