Metadata-Version: 2.1
Name: dash-google-oauth
Version: 1.2
Summary: Authenticate to Dash app using Google OAuth
Home-page: https://github.com/hossein-jazayeri/dash-google-oauth
Author: Hossein Jazayeri
Author-email: hossein.jaza@gmail.com
License: MIT
Platform: UNKNOWN
Classifier: Framework :: Flask
Classifier: License :: OSI Approved :: MIT License
Classifier: Programming Language :: Python :: 3
Classifier: Programming Language :: Python :: 3.6
Classifier: Programming Language :: Python :: 3.7
Classifier: Programming Language :: Python :: 3.8
Requires-Python: >=3.6
Requires-Dist: dash (>=1.2.0)
Requires-Dist: Flask (>=1.1.1)
Requires-Dist: authlib (==0.11)
Requires-Dist: ua-parser
Requires-Dist: chart-studio (>=1.0.0)
